crisper_api_client/__init__.py
crisper_api_client/api/__init__.py
crisper_api_client/api/api/__init__.py
crisper_api_client/api/api/api_v1_assistant_ask_a_retrieve.py
crisper_api_client/api/api/api_v1_assistant_ask_create.py
crisper_api_client/api/api/api_v1_assistant_create.py
crisper_api_client/api/api/api_v1_assistant_destroy.py
crisper_api_client/api/api/api_v1_assistant_knowledge_source_create.py
crisper_api_client/api/api/api_v1_assistant_list.py
crisper_api_client/api/api/api_v1_assistant_retrieve.py
crisper_api_client/client.py
crisper_api_client/errors.py
crisper_api_client/models/__init__.py
crisper_api_client/models/answer.py
crisper_api_client/models/assistant.py
crisper_api_client/models/knowledge_source.py
crisper_api_client/models/knowledge_source_content_type.py
crisper_api_client/models/paginated_assistant_list.py
crisper_api_client/models/question.py
crisper_api_client/py.typed
crisper_api_client/sdk.py
crisper_api_client/serivces/assistant_service.py
crisper_api_client/types.py
crisper_ai-0.3.4.dist-info/METADATA
crisper_ai-0.3.4.dist-info/WHEEL
crisper_ai-0.3.4.dist-info/RECORD
